d8s_file_system/__init__.py
d8s_file_system/atomic_writes.py
d8s_file_system/directories.py
d8s_file_system/directories_temp_utils.py
d8s_file_system/files.py
d8s_file_system/files_temp_utils.py
tests/__init__.py
tests/test_atomic_writes.py
tests/test_directories.py
tests/test_files.py
d8s_file_system-0.10.0.dist-info/COPYING
d8s_file_system-0.10.0.dist-info/COPYING.LESSER
d8s_file_system-0.10.0.dist-info/METADATA
d8s_file_system-0.10.0.dist-info/WHEEL
d8s_file_system-0.10.0.dist-info/top_level.txt
d8s_file_system-0.10.0.dist-info/zip-safe
d8s_file_system-0.10.0.dist-info/RECORD
