Metadata-Version: 2.1
Name: d8s-file-system
Version: 0.10.0
Summary: Democritus functions for working with files and directories.
Home-page: https://github.com/democritus-project/d8s-file-system
Author: Floyd Hightower
Author-email: floyd.hightower27@gmail.com
License: GNU Lesser General Public License v3
Keywords: democritus,utility,python,directories,directories-utility,directories,file-system,files,files-utility
Platform: UNKNOWN
Classifier: Development Status :: 2 - Pre-Alpha
Classifier: Intended Audience :: Developers
Classifier: License :: OSI Approved :: GNU Lesser General Public License v3 or later (LGPLv3+)
Classifier: Natural Language :: English
Classifier: Programming Language :: Python :: 3
Classifier: Programming Language :: Python :: 3.4
Classifier: Programming Language :: Python :: 3.5
Classifier: Programming Language :: Python :: 3.6
Classifier: Programming Language :: Python :: 3.7
Classifier: Programming Language :: Python :: 3.8
Classifier: Programming Language :: Python :: 3.9
Requires-Dist: atomicwrites
Requires-Dist: d8s-hashes (==0.*)
Requires-Dist: importlib-metadata ; python_version < "3.8"
